Workbook

Sheet Read Me
A1: 4sight Sample Dataset — Data Quality Review & Signal Efficacy Analysis
A3: Scope
A4: Vendor file: Sample_Dataset.xlsx — 1,038 rows, 19-Nov-2015 to 06-Jan-2020. Columns: Date, Signal, Open, High, Low, Close, Adj Close.
A6: Contents
A7: QC Log — every quality-check exception found, the corrected value, and the rule applied (39 items).
A8: Data (Cleaned) — corrected series. Amber cells were changed; the validation columns re-run the checks live.
A9: Signal Analysis — efficacy metrics, all computed with worksheet formulas off the cleaned data.
A11: Headline conclusions
A12: 1. The file fails basic integrity checks: 5 rows dated on non-trading days, 1 impossible Close, 3 corrupt Adj Close values,
A13: 8 High/Low values inconsistent with Open/Close, an 11-session frozen Close, 6 Signals coded 0, and a missing week.
A14: 2. The Signal is not independent information — it is ~88% explained by the ETF price level alone (Signal ~= AdjClose / 8.13).
A15: 3. The part of the Signal not explained by TODAY'S price is explained by prices 3-7 sessions LATER. Correlation of the
... A26: a small-cap Russell 2000 ETF, not a broad market ETF as described. To be confirmed against an independent price source.

Sheet QC Log
A1: Quality check exceptions and corrections applied
A3: # | B3: Check | C3: Date | D3: Field | E3: Original value | F3: Corrected value | G3: Why it is an error | H3: Correction rule applied
A4: 1 | B4: QC1 Calendar | C4: 2017-07-04 | D4: entire row | E4: present | F4: row deleted | G4: US Independence Day (market closed); OHLC = previous session +$0.10, Signal duplicates next session | H4: Delete (fabricated / duplicated session)
A5: 2 | B5: QC1 Calendar | C5: 2018-05-19 | D5: entire row | E5: present | F5: row deleted | G5: Saturday; OHLC duplicates Mon 21-May, Signal duplicates Thu 17-May | H5: Delete (fabricated / duplicated session)
A6: 3 | B6: QC1 Calendar | C6: 2018-05-20 | D6: entire row | E6: present | F6: row deleted | G6: Sunday; OHLC duplicates Tue 22-May, Signal duplicates Fri 18-May | H6: Delete (fabricated / duplicated session)
A7: 4 | B7: QC1 Calendar | C7: 2018-06-23 | D7: entire row | E7: present | F7: row deleted | G7: Saturday; OHLC duplicates Mon 25-Jun, Signal duplicates Thu 21-Jun | H7: Delete (fabricated / duplicated session)
A8: 5 | B8: QC1 Calendar | C8: 2018-06-24 | D8: entire row | E8: present | F8: row deleted | G8: Sunday; OHLC duplicates Tue 26-Jun, Signal duplicates Fri 22-Jun | H8: Delete (fabricated / duplicated session)
A9: 6 | B9: QC2 Range | C9: 2018-03-19 | D9: Close | E9: 196.28 | F9: 156.28 | G9: Close 196.28 far outside the session range (Low 154.45 / High 157.21) and a +25% one-day jump reversed the next day; leading digit 1->9 keying error | H9: Re-derive Close = Adj Close / adjustment factor of adjacent session
A10: 7 | B10: QC3 Adj Close | C10: 2016-12-05 | D10: Adj Close | E10: 166.17508 | F10: 126.17509 | G10: Adj Close 166.18 exceeds Close 133.15; implied adj factor 1.248 vs 0.948 on either side (+40 keying error) | H10: Re-derive Adj Close = Close x adjustment factor of adjacent session
A11: 8 | B11: QC3 Adj Close | C11: 2017-03-27 | D11: Adj Close | E11: 158.57764 | F11: 128.57764 | G11: Adj Close 158.58 exceeds Close 134.74; implied adj factor 1.177 vs 0.954 on either side (+30 keying error) | H11: Re-derive Adj Close = Close x adjustment factor of adjacent session
A12: 9 | B12: QC3 Adj Close | C12: 2018-10-10 | D12: Adj Close | E12: -152.27785 | F12: 152.27785 | G12: Adj Close -152.28 is negative; a price can never be < 0. |value| matches the neighbouring adj factor exactly | H12: Flip sign
A13: 10 | B13: QC4 OHLC | C13: 2017-08-07 | D13: High | E13: 140.35 | F13: 140.44 | G13: High (140.35) below the session Open/Close (140.44) - logically impossible | H13: High = max(Open, High, Low, Close)
A14: 11 | B14: QC4 OHLC | C14: 2018-03-07 | D14: Low | E14: 157.22 | F14: 154.46001 | G14: Low (157.22) above the session Open/Close (154.46) - logically impossible | H14: Low = min(Open, High, Low, Close)
A15: 12 | B15: QC4 OHLC | C15: 2018-07-16 | D15: Low | E15: 169.96001 | F15: 166.77 | G15: Low (169.96) above the session Open/Close (166.77) - logically impossible | H15: Low = min(Open, High, Low, Close)
A16: 13 | B16: QC4 OHLC | C16: 2018-10-19 | D16: Low | E16: 154.74 | F16: 153.36 | G16: Low (154.74) above the session Open/Close (153.36) - logically impossible | H16: Low = min(Open, High, Low, Close)
A17: 14 | B17: QC4 OHLC | C17: 2018-12-06 | D17: High | E17: 147.1 | F17: 147.2 | G17: High (147.10) below the session Open/Close (147.20) - logically impossible | H17: High = max(Open, High, Low, Close)
A18: 15 | B18: QC4 OHLC | C18: 2019-06-10 | D18: Low | E18: 152.45 | F18: 151.45 | G18: Low (152.45) above the session Open/Close (151.45) - logically impossible | H18: Low = min(Open, High, Low, Close)
A19: 16 | B19: QC4 OHLC | C19: 2019-09-24 | D19: Low | E19: 152.84 | F19: 152.42999 | G19: Low (152.84) above the session Open/Close (152.43) - logically impossible | H19: Low = min(Open, High, Low, Close)
A20: 17 | B20: QC4 OHLC | C20: 2019-10-17 | D20: High | E20: 153.30999 | F20: 153.34 | G20: High (153.31) below the session Open/Close (153.34) - logically impossible | H20: High = max(Open, High, Low, Close)
A21: 18 | B21: QC5 Stale | C21: 2017-09-08 | D21: Close, Adj Close | E21: 139.11 | F21: retained, flagged | G21: Close & Adj Close frozen at 139.110001 / 133.321198 for 11 consecutive sessions while Open/High/Low keep moving; first repeat of the 07-Sep close, not provably wrong | H21: Flag; retain
A22: 19 | B22: QC5 Stale | C22: 2017-09-11 | D22: Close, Adj Close | E22: 139.11 | F22: NaN (re-source) | G22: Close & Adj Close frozen at 139.110001 / 133.321198 for 11 consecutive sessions while Open/High/Low keep moving; the frozen Close sits below the session Low, so it is provably wrong | H22: Set to NaN and re-source from an independent vendor (linear interpolation used for analysis only)
A23: 20 | B23: QC5 Stale | C23: 2017-09-12 | D23: Close, Adj Close | E23: 139.11 | F23: NaN (re-source) | G23: Close & Adj Close frozen at 139.110001 / 133.321198 for 11 consecutive sessions while Open/High/Low keep moving; the frozen Close sits below the session Low, so it is provably wrong | H23: Set to NaN and re-source from an independent vendor (linear interpolation used for analysis only)
A24: 21 | B24: QC5 Stale | C24: 2017-09-13 | D24: Close, Adj Close | E24: 139.11 | F24: NaN (re-source) | G24: Close & Adj Close frozen at 139.110001 / 133.321198 for 11 consecutive sessions while Open/High/Low keep moving; the frozen Close sits below the session Low, so it is provably wrong | H24: Set to NaN and re-source from an independent vendor (linear interpolation used for analysis only)
A25: 22 | B25: QC5 Stale | C25: 2017-09-14 | D25: Close, Adj Close | E25: 139.11 | F25: NaN (re-source) | G25: Close & Adj Close frozen at 139.110001 / 133.321198 for 11 consecutive sessions while Open/High/Low keep moving; the frozen Close sits below the session Low, so it is provably wrong | H25: Set to NaN and re-source from an independent vendor (linear interpolation used for analysis only)
A26: 23 | B26: QC5 Stale | C26: 2017-09-15 | D26: Close, Adj Close | E26: 139.11 | F26: NaN (re-source) | G26: Close & Adj Close frozen at 139.110001 / 133.321198 for 11 consecutive sessions while Open/High/Low keep moving; the frozen Close sits below the session Low, so it is provably wrong | H26: Set to NaN and re-source from an independent vendor (linear interpolation used for analysis only)
A27: 24 | B27: QC5 Stale | C27: 2017-09-18 | D27: Close, Adj Close | E27: 139.11 | F27: NaN (re-source) | G27: Close & Adj Close frozen at 139.110001 / 133.321198 for 11 consecutive sessions while Open/High/Low keep moving; the frozen Close sits below the session Low, so it is provably wrong | H27: Set to NaN and re-source from an independent vendor (linear interpolation used for analysis only)
A28: 25 | B28: QC5 Stale | C28: 2017-09-19 | D28: Close, Adj Close | E28: 139.11 | F28: NaN (re-source) | G28: Close & Adj Close frozen at 139.110001 / 133.321198 for 11 consecutive sessions while Open/High/Low keep moving; the frozen Close sits below the session Low, so it is provably wrong | H28: Set to NaN and re-source from an independent vendor (linear interpolation used for analysis only)
A29: 26 | B29: QC5 Stale | C29: 2017-09-20 | D29: Close, Adj Close | E29: 139.11 | F29: NaN (re-source) | G29: Close & Adj Close frozen at 139.110001 / 133.321198 for 11 consecutive sessions while Open/High/Low keep moving; the frozen Close sits below the session Low, so it is provably wrong | H29: Set to NaN and re-source from an independent vendor (linear interpolation used for analysis only)
A30: 27 | B30: QC5 Stale | C30: 2017-09-21 | D30: Close, Adj Close | E30: 139.11 | F30: NaN (re-source) | G30: Close & Adj Close frozen at 139.110001 / 133.321198 for 11 consecutive sessions while Open/High/Low keep moving; the frozen Close sits below the session Low, so it is provably wrong | H30: Set to NaN and re-source from an independent vendor (linear interpolation used for analysis only)
A31: 28 | B31: QC5 Stale | C31: 2017-09-22 | D31: Close, Adj Close | E31: 139.11 | F31: NaN (re-source) | G31: Close & Adj Close frozen at 139.110001 / 133.321198 for 11 consecutive sessions while Open/High/Low keep moving; the frozen Close sits below the session Low, so it is provably wrong | H31: Set to NaN and re-source from an independent vendor (linear interpolation used for analysis only)
A32: 29 | B32: QC6 Signal | C32: 2019-12-27 | D32: Signal | E32: 0 | G32: Signal exactly 0.000000 for the last 6 sessions; the other 1,027 observations never fall below 10.58 - a missing value written as zero | H32: Set to NaN and exclude from analysis; request re-delivery
A33: 30 | B33: QC6 Signal | C33: 2019-12-30 | D33: Signal | E33: 0 | G33: Signal exactly 0.000000 for the last 6 sessions; the other 1,027 observations never fall below 10.58 - a missing value written as zero | H33: Set to NaN and exclude from analysis; request re-delivery
A34: 31 | B34: QC6 Signal | C34: 2019-12-31 | D34: Signal | E34: 0 | G34: Signal exactly 0.000000 for the last 6 sessions; the other 1,027 observations never fall below 10.58 - a missing value written as zero | H34: Set to NaN and exclude from analysis; request re-delivery
A35: 32 | B35: QC6 Signal | C35: 2020-01-02 | D35: Signal | E35: 0 | G35: Signal exactly 0.000000 for the last 6 sessions; the other 1,027 observations never fall below 10.58 - a missing value written as zero | H35: Set to NaN and exclude from analysis; request re-delivery
A36: 33 | B36: QC6 Signal | C36: 2020-01-03 | D36: Signal | E36: 0 | G36: Signal exactly 0.000000 for the last 6 sessions; the other 1,027 observations never fall below 10.58 - a missing value written as zero | H36: Set to NaN and exclude from analysis; request re-delivery
A37: 34 | B37: QC6 Signal | C37: 2020-01-06 | D37: Signal | E37: 0 | G37: Signal exactly 0.000000 for the last 6 sessions; the other 1,027 observations never fall below 10.58 - a missing value written as zero | H37: Set to NaN and exclude from analysis; request re-delivery
A38: 35 | B38: QC7 Gaps | C38: 2018-11-12 | D38: entire row | E38: absent | F38: placeholder row (NaN) | G38: Trading session missing; 09-Nov-2018 is followed directly by 19-Nov-2018, a full week of data absent | H38: Insert placeholder row; request the missing week from the vendor
A39: 36 | B39: QC7 Gaps | C39: 2018-11-13 | D39: entire row | E39: absent | F39: placeholder row (NaN) | G39: Trading session missing; 09-Nov-2018 is followed directly by 19-Nov-2018, a full week of data absent | H39: Insert placeholder row; request the missing week from the vendor
A40: 37 | B40: QC7 Gaps | C40: 2018-11-14 | D40: entire row | E40: absent | F40: placeholder row (NaN) | G40: Trading session missing; 09-Nov-2018 is followed directly by 19-Nov-2018, a full week of data absent | H40: Insert placeholder row; request the missing week from the vendor
A41: 38 | B41: QC7 Gaps | C41: 2018-11-15 | D41: entire row | E41: absent | F41: placeholder row (NaN) | G41: Trading session missing; 09-Nov-2018 is followed directly by 19-Nov-2018, a full week of data absent | H41: Insert placeholder row; request the missing week from the vendor
A42: 39 | B42: QC7 Gaps | C42: 2018-11-16 | D42: entire row | E42: absent | F42: placeholder row (NaN) | G42: Trading session missing; 09-Nov-2018 is followed directly by 19-Nov-2018, a full week of data absent | H42: Insert placeholder row; request the missing week from the vendor
A45: Total exceptions | B45: =COUNTA(A4:A42) -> 39

Sheet Data (Cleaned)
A1: Cleaned dataset — amber = value corrected (hover for the original)
A3: Date | B3: Signal | C3: Open | D3: High | E3: Low | F3: Close | G3: Adj Close | H3: Adj Close (analysis) | I3: OHLC check | J3: Adj factor | K3: Daily return | L3: Fwd 5d return | M3: Signal z (60d) | N3: Price z (60d) | O3: Signal residual
A4: 42327 | B4: 13.76854 | C4: 116.44 | D4: 116.65 | E4: 115.74 | F4: 116.06 | G4: 108.2816 | H4: 108.2816 | I4: =IF(COUNT(C4:F4)<4,"",IF(OR(D4<MAX(C4,F4)-0.000001,E4>MIN(C4,F4)+0.000001),"FAIL","OK")) -> OK | J4: =IF(COUNT(F4,G4)<2,"",G4/F4) -> 0.93297952 | L4: =H9/H4-1 -> 0.030673688 | O4: =IF(COUNT(B4)=0,"",B4-('Signal Analysis'!$C$6+'Signal Analysis'!$C$5*H4)) -> 0.75418652
A5: 42328 | B5: 13.608819 | C5: 116.48 | D5: 117.36 | E5: 116.38 | F5: 116.81 | G5: 108.98132 | H5: 108.98132 | I5: =IF(COUNT(C5:F5)<4,"",IF(OR(D5<MAX(C5,F5)-0.000001,E5>MIN(C5,F5)+0.000001),"FAIL","OK")) -> OK | J5: =IF(COUNT(F5,G5)<2,"",G5/F5) -> 0.93297941 | K5: =H5/H4-1 -> 0.0064620581 | L5: =H10/H5-1 -> 0.019604534 | O5: =IF(COUNT(B5)=0,"",B5-('Signal Analysis'!$C$6+'Signal Analysis'!$C$5*H5)) -> 0.49874886
A6: 42331 | B6: 12.990589 | C6: 116.71 | D6: 117.89 | E6: 116.68 | F6: 117.39 | G6: 109.52245 | H6: 109.52245 | I6: =IF(COUNT(C6:F6)<4,"",IF(OR(D6<MAX(C6,F6)-0.000001,E6>MIN(C6,F6)+0.000001),"FAIL","OK")) -> OK | J6: =IF(COUNT(F6,G6)<2,"",G6/F6) -> 0.93297942 | K6: =H6/H5-1 -> 0.0049653462 | L6: =H11/H6-1 -> 0.021296492 | O6: =IF(COUNT(B6)=0,"",B6-('Signal Analysis'!$C$6+'Signal Analysis'!$C$5*H6)) -> -0.19350344
A7: 42332 | B7: 12.667435 | C7: 116.88 | D7: 118.42 | E7: 116.56 | F7: 118.25 | G7: 110.32484 | H7: 110.32484 | I7: =IF(COUNT(C7:F7)<4,"",IF(OR(D7<MAX(C7,F7)-0.000001,E7>MIN(C7,F7)+0.000001),"FAIL","OK")) -> OK | J7: =IF(COUNT(F7,G7)<2,"",G7/F7) -> 0.93297959 | K7: =H7/H6-1 -> 0.0073262055 | L7: =H12/H7-1 -> 0.0029597143 | O7: =IF(COUNT(B7)=0,"",B7-('Signal Analysis'!$C$6+'Signal Analysis'!$C$5*H7)) -> -0.62641733
A8: 42333 | B8: 13.01991 | C8: 118.3 | D8: 119.32 | E8: 118.11 | F8: 119.17 | G8: 111.18316 | H8: 111.18316 | I8: =IF(COUNT(C8:F8)<4,"",IF(OR(D8<MAX(C8,F8)-0.000001,E8>MIN(C8,F8)+0.000001),"FAIL","OK")) -> OK | J8: =IF(COUNT(F8,G8)<2,"",G8/F8) -> 0.93297945 | K8: =H8/H7-1 -> 0.0077799526 | L8: =H13/H8-1 -> -0.021565775 | O8: =IF(COUNT(B8)=0,"",B8-('Signal Analysis'!$C$6+'Signal Analysis'!$C$5*H8)) -> -0.39135429
A9: 42335 | B9: 12.879819 | C9: 119.27 | D9: 119.9 | E9: 118.88 | F9: 119.62 | G9: 111.603 | H9: 111.603 | I9: =IF(COUNT(C9:F9)<4,"",IF(OR(D9<MAX(C9,F9)-0.000001,E9>MIN(C9,F9)+0.000001),"FAIL","OK")) -> OK | J9: =IF(COUNT(F9,G9)<2,"",G9/F9) -> 0.93297939 | K9: =H9/H8-1 -> 0.0037760935 | L9: =H14/H9-1 -> -0.015381979 | O9: =IF(COUNT(B9)=0,"",B9-('Signal Analysis'!$C$6+'Signal Analysis'!$C$5*H9)) -> -0.58887584
A10: 42338 | B10: 13.184791 | C10: 120.02 | D10: 120.07 | E10: 119.05 | F10: 119.1 | G10: 111.11785 | H10: 111.11785 | I10: =IF(COUNT(C10:F10)<4,"",IF(OR(D10<MAX(C10,F10)-0.000001,E10>MIN(C10,F10)+0.000001),"FAIL","OK")) -> OK | J10: =IF(COUNT(F10,G10)<2,"",G10/F10) -> 0.93297945 | K10: =H10/H9-1 -> -0.0043470696 | L10: =H15/H10-1 -> -0.025944562 | O10: =IF(COUNT(B10)=0,"",B10-('Signal Analysis'!$C$6+'Signal Analysis'!$C$5*H10)) -> -0.21753921
A11: 42339 | B11: 12.922631 | C11: 119.61 | D11: 119.91 | E11: 118.9 | F11: 119.89 | G11: 111.8549 | H11: 111.8549 | I11: =IF(COUNT(C11:F11)<4,"",IF(OR(D11<MAX(C11,F11)-0.000001,E11>MIN(C11,F11)+0.000001),"FAIL","OK")) -> OK | J11: =IF(COUNT(F11,G11)<2,"",G11/F11) -> 0.93297938 | K11: =H11/H10-1 -> 0.0066330116 | L11: =H16/H11-1 -> -0.037701201 | O11: =IF(COUNT(B11)=0,"",B11-('Signal Analysis'!$C$6+'Signal Analysis'!$C$5*H11)) -> -0.5805215
A12: 42340 | B12: 13.118076 | C12: 119.73 | D12: 120.04 | E12: 118.45 | F12: 118.6 | G12: 110.65137 | H12: 110.65137 | I12: =IF(COUNT(C12:F12)<4,"",IF(OR(D12<MAX(C12,F12)-0.000001,E12>MIN(C12,F12)+0.000001),"FAIL","OK")) -> OK | J12: =IF(COUNT(F12,G12)<2,"",G12/F12) -> 0.9329795 | K12: =H12/H11-1 -> -0.010759743 | L12: =H17/H12-1 -> -0.038111404 | O12: =IF(COUNT(B12)=0,"",B12-('Signal Analysis'!$C$6+'Signal Analysis'!$C$5*H12)) -> -0.2204436
A13: 42341 | B13: 12.91654 | C13: 118.93 | D13: 119.45 | E13: 116.14 | F13: 116.6 | G13: 108.78541 | H13: 108.78541 | I13: =IF(COUNT(C13:F13)<4,"",IF(OR(D13<MAX(C13,F13)-0.000001,E13>MIN(C13,F13)+0.000001),"FAIL","OK")) -> OK | J13: =IF(COUNT(F13,G13)<2,"",G13/F13) -> 0.9329795 | K13: =H13/H12-1 -> -0.016863407 | L13: =H18/H13-1 -> -0.018353261 | O13: =IF(COUNT(B13)=0,"",B13-('Signal Analysis'!$C$6+'Signal Analysis'!$C$5*H13)) -> -0.16673016
A14: 42342 | B14: 13.155278 | C14: 116.6 | D14: 117.93 | E14: 116.34 | F14: 117.78 | G14: 109.88632 | H14: 109.88632 | I14: =IF(COUNT(C14:F14)<4,"",IF(OR(D14<MAX(C14,F14)-0.000001,E14>MIN(C14,F14)+0.000001),"FAIL","OK")) -> OK | J14: =IF(COUNT(F14,G14)<2,"",G14/F14) -> 0.93297948 | K14: =H14/H13-1 -> 0.010120052 | L14: =H19/H14-1 -> -0.049838641 | O14: =IF(COUNT(B14)=0,"",B14-('Signal Analysis'!$C$6+'Signal Analysis'!$C$5*H14)) -> -0.078588819
A15: 42345 | B15: 12.430221 | C15: 117.64 | D15: 117.67 | E15: 115.51 | F15: 116.01 | G15: 108.23495 | H15: 108.23495 | I15: =IF(COUNT(C15:F15)<4,"",IF(OR(D15<MAX(C15,F15)-0.000001,E15>MIN(C15,F15)+0.000001),"FAIL","OK")) -> OK | J15: =IF(COUNT(F15,G15)<2,"",G15/F15) -> 0.93297944 | K15: =H15/H14-1 -> -0.015028031 | L15: =H20/H15-1 -> -0.04223755 | O15: =IF(COUNT(B15)=0,"",B15-('Signal Analysis'!$C$6+'Signal Analysis'!$C$5*H15)) -> -0.57775013
A16: 42346 | B16: 13.030335 | C16: 114.96 | D16: 116.01 | E16: 114.46 | F16: 115.37 | G16: 107.63783 | H16: 107.63783 | I16: =IF(COUNT(C16:F16)<4,"",IF(OR(D16<MAX(C16,F16)-0.000001,E16>MIN(C16,F16)+0.000001),"FAIL","OK")) -> OK | J16: =IF(COUNT(F16,G16)<2,"",G16/F16) -> 0.93297937 | K16: =H16/H15-1 -> -0.0055168318 | L16: =H21/H16-1 -> -0.02305614 | O16: =IF(COUNT(B16)=0,"",B16-('Signal Analysis'!$C$6+'Signal Analysis'!$C$5*H16)) -> 0.10404463
... A62: 42416 | B62: 11.407893 | C62: 97.790001 | D62: 99.099998 | E62: 97.220001 | F62: 98.879997 | G62: 92.653389 | H62: 92.653389 | I62: =IF(COUNT(C62:F62)<4,"",IF(OR(D62<MAX(C62,F62)-0.000001,E62>MIN(C62,F62)+0.000001),"FAIL","OK")) -> OK | J62: =IF(COUNT(F62,G62)<2,"",G62/F62) -> 0.93702864 | K62: =H62/H61-1 -> 0.023708487 | L62: =H67/H62-1 -> 0.017799349 | O62: =IF(COUNT(B62)=0,"",B62-('Signal Analysis'!$C$6+'Signal Analysis'!$C$5*H62)) -> 0.5313606
A63: 42417 | B63: 11.078253 | C63: 99.57 | D63: 101.09 | E63: 99.529999 | F63: 100.43 | G63: 94.105797 | H63: 94.105797 | I63: =IF(COUNT(C63:F63)<4,"",IF(OR(D63<MAX(C63,F63)-0.000001,E63>MIN(C63,F63)+0.000001),"FAIL","OK")) -> OK | J63: =IF(COUNT(F63,G63)<2,"",G63/F63) -> 0.93702875 | K63: =H63/H62-1 -> 0.015675714 | L63: =H68/H63-1 -> 0.011749595 | M63: =IF(COUNT(B4:B63)<60,"",(B63-AVERAGE(B4:B63))/STDEV(B4:B63)) -> -1.0363275 | N63: =(H63-AVERAGE(H4:H63))/STDEV(H4:H63) -> -0.93771379 | O63: =IF(COUNT(B63)=0,"",B63-('Signal Analysis'!$C$6+'Signal Analysis'!$C$5*H63)) -> 0.0030426444
A64: 42418 | B64: 11.882122 | C64: 100.51 | D64: 100.64 | E64: 99.540001 | F64: 99.949997 | G64: 93.656013 | H64: 93.656013 | I64: =IF(COUNT(C64:F64)<4,"",IF(OR(D64<MAX(C64,F64)-0.000001,E64>MIN(C64,F64)+0.000001),"FAIL","OK")) -> OK | J64: =IF(COUNT(F64,G64)<2,"",G64/F64) -> 0.93702867 | K64: =H64/H63-1 -> -0.0047795568 | L64: =H69/H64-1 -> 0.025912869 | M64: =IF(COUNT(B5:B64)<60,"",(B64-AVERAGE(B5:B64))/STDEV(B5:B64)) -> -0.1461968 | N64: =(H64-AVERAGE(H5:H64))/STDEV(H5:H64) -> -0.9668357 | O64: =IF(COUNT(B64)=0,"",B64-('Signal Analysis'!$C$6+'Signal Analysis'!$C$5*H64)) -> 0.86843899
A65: 42419 | B65: 11.311126 | C65: 99.559998 | D65: 100.56 | E65: 99.110001 | F65: 100.45 | G65: 94.124527 | H65: 94.124527 | I65: =IF(COUNT(C65:F65)<4,"",IF(OR(D65<MAX(C65,F65)-0.000001,E65>MIN(C65,F65)+0.000001),"FAIL","OK")) -> OK | J65: =IF(COUNT(F65,G65)<2,"",G65/F65) -> 0.93702867 | K65: =H65/H64-1 -> 0.0050024978 | L65: =H70/H65-1 -> 0.027277258 | M65: =IF(COUNT(B6:B65)<60,"",(B65-AVERAGE(B6:B65))/STDEV(B6:B65)) -> -0.75072831 | N65: =(H65-AVERAGE(H6:H65))/STDEV(H6:H65) -> -0.87239263 | O65: =IF(COUNT(B65)=0,"",B65-('Signal Analysis'!$C$6+'Signal Analysis'!$C$5*H65)) -> 0.23335383
A66: 42422 | B66: 11.068751 | C66: 101.34 | D66: 102.01 | E66: 101.24 | F66: 101.57 | G66: 95.173996 | H66: 95.173996 | I66: =IF(COUNT(C66:F66)<4,"",IF(OR(D66<MAX(C66,F66)-0.000001,E66>MIN(C66,F66)+0.000001),"FAIL","OK")) -> OK | J66: =IF(COUNT(F66,G66)<2,"",G66/F66) -> 0.93702861 | K66: =H66/H65-1 -> 0.011149793 | L66: =H71/H66-1 -> 0.011420767 | M66: =IF(COUNT(B7:B66)<60,"",(B66-AVERAGE(B7:B66))/STDEV(B7:B66)) -> -0.99097727 | N66: =(H66-AVERAGE(H7:H66))/STDEV(H7:H66) -> -0.70076674 | O66: =IF(COUNT(B66)=0,"",B66-('Signal Analysis'!$C$6+'Signal Analysis'!$C$5*H66)) -> -0.15258091
A67: 42423 | B67: 12.18319 | C67: 101.24 | D67: 101.49 | E67: 100.55 | F67: 100.64 | G67: 94.302559 | H67: 94.302559 | I67: =IF(COUNT(C67:F67)<4,"",IF(OR(D67<MAX(C67,F67)-0.000001,E67>MIN(C67,F67)+0.000001),"FAIL","OK")) -> OK | J67: =IF(COUNT(F67,G67)<2,"",G67/F67) -> 0.93702862 | K67: =H67/H66-1 -> -0.009156251 | L67: =H72/H67-1 -> 0.042726688 | M67: =IF(COUNT(B8:B67)<60,"",(B67-AVERAGE(B8:B67))/STDEV(B8:B67)) -> 0.28097411 | N67: =(H67-AVERAGE(H8:H67))/STDEV(H8:H67) -> -0.79477174 | O67: =IF(COUNT(B67)=0,"",B67-('Signal Analysis'!$C$6+'Signal Analysis'!$C$5*H67)) -> 1.0810642
A68: 42424 | B68: 12.12888 | C68: 99.620003 | D68: 101.82 | E68: 98.970001 | F68: 101.61 | G68: 95.211502 | H68: 95.211502 | I68: =IF(COUNT(C68:F68)<4,"",IF(OR(D68<MAX(C68,F68)-0.000001,E68>MIN(C68,F68)+0.000001),"FAIL","OK")) -> OK | J68: =IF(COUNT(F68,G68)<2,"",G68/F68) -> 0.93702885 | K68: =H68/H67-1 -> 0.0096385826 | L68: =H73/H68-1 -> 0.043400964 | M68: =IF(COUNT(B9:B68)<60,"",(B68-AVERAGE(B9:B68))/STDEV(B9:B68)) -> 0.23911933 | N68: =(H68-AVERAGE(H9:H68))/STDEV(H9:H68) -> -0.6405226 | O68: =IF(COUNT(B68)=0,"",B68-('Signal Analysis'!$C$6+'Signal Analysis'!$C$5*H68)) -> 0.90241789
A69: 42425 | B69: 12.271808 | C69: 101.79 | D69: 102.6 | E69: 101.39 | F69: 102.54 | G69: 96.082909 | H69: 96.082909 | I69: =IF(COUNT(C69:F69)<4,"",IF(OR(D69<MAX(C69,F69)-0.000001,E69>MIN(C69,F69)+0.000001),"FAIL","OK")) -> OK | J69: =IF(COUNT(F69,G69)<2,"",G69/F69) -> 0.93702856 | K69: =H69/H68-1 -> 0.0091523291 | L69: =H74/H69-1 -> 0.044763133 | M69: =IF(COUNT(B10:B69)<60,"",(B69-AVERAGE(B10:B69))/STDEV(B10:B69)) -> 0.41929319 | N69: =(H69-AVERAGE(H10:H69))/STDEV(H10:H69) -> -0.48936162 | O69: =IF(COUNT(B69)=0,"",B69-('Signal Analysis'!$C$6+'Signal Analysis'!$C$5*H69)) -> 0.92614358
A70: 42426 | B70: 12.159678 | C70: 103.06 | D70: 103.47 | E70: 102.7 | F70: 103.19 | G70: 96.691986 | H70: 96.691986 | I70: =IF(COUNT(C70:F70)<4,"",IF(OR(D70<MAX(C70,F70)-0.000001,E70>MIN(C70,F70)+0.000001),"FAIL","OK")) -> OK | J70: =IF(COUNT(F70,G70)<2,"",G70/F70) -> 0.93702863 | K70: =H70/H69-1 -> 0.0063390774 | L70: =H75/H70-1 -> 0.043899636 | M70: =IF(COUNT(B11:B70)<60,"",(B70-AVERAGE(B11:B70))/STDEV(B11:B70)) -> 0.31450929 | N70: =(H70-AVERAGE(H11:H70))/STDEV(H11:H70) -> -0.3732816 | O70: =IF(COUNT(B70)=0,"",B70-('Signal Analysis'!$C$6+'Signal Analysis'!$C$5*H70)) -> 0.73069625
A71: 42429 | B71: 12.648369 | C71: 103.13 | D71: 104.03 | E71: 102.72 | F71: 102.73 | G71: 96.260956 | H71: 96.260956 | I71: =IF(COUNT(C71:F71)<4,"",IF(OR(D71<MAX(C71,F71)-0.000001,E71>MIN(C71,F71)+0.000001),"FAIL","OK")) -> OK | J71: =IF(COUNT(F71,G71)<2,"",G71/F71) -> 0.93702865 | K71: =H71/H70-1 -> -0.0044577634 | L71: =H76/H71-1 -> 0.05996291 | M71: =IF(COUNT(B12:B71)<60,"",(B71-AVERAGE(B12:B71))/STDEV(B12:B71)) -> 0.90404134 | N71: =(H71-AVERAGE(H12:H71))/STDEV(H12:H71) -> -0.41193927 | O71: =IF(COUNT(B71)=0,"",B71-('Signal Analysis'!$C$6+'Signal Analysis'!$C$5*H71)) -> 1.2783491
A72: 42430 | B72: 11.991283 | C72: 103.62 | D72: 104.94 | E72: 103.07 | F72: 104.94 | G72: 98.331795 | H72: 98.331795 | I72: =IF(COUNT(C72:F72)<4,"",IF(OR(D72<MAX(C72,F72)-0.000001,E72>MIN(C72,F72)+0.000001),"FAIL","OK")) -> OK | J72: =IF(COUNT(F72,G72)<2,"",G72/F72) -> 0.93702871 | K72: =H72/H71-1 -> 0.021512762 | L72: =H77/H72-1 -> 0.012578454 | M72: =IF(COUNT(B13:B72)<60,"",(B72-AVERAGE(B13:B72))/STDEV(B13:B72)) -> 0.14624967 | N72: =(H72-AVERAGE(H13:H72))/STDEV(H13:H72) -> -0.058050519 | O72: =IF(COUNT(B72)=0,"",B72-('Signal Analysis'!$C$6+'Signal Analysis'!$C$5*H72)) -> 0.33798839
A73: 42431 | B73: 12.243965 | C73: 104.79 | D73: 106.09 | E73: 104.59 | F73: 106.02 | G73: 99.343773 | H73: 99.343773 | I73: =IF(COUNT(C73:F73)<4,"",IF(OR(D73<MAX(C73,F73)-0.000001,E73>MIN(C73,F73)+0.000001),"FAIL","OK")) -> OK | J73: =IF(COUNT(F73,G73)<2,"",G73/F73) -> 0.93702863 | K73: =H73/H72-1 -> 0.010291463 | L73: =H78/H73-1 -> 0.0073573207 | M73: =IF(COUNT(B14:B73)<60,"",(B73-AVERAGE(B14:B73))/STDEV(B14:B73)) -> 0.4722734 | N73: =(H73-AVERAGE(H14:H73))/STDEV(H14:H73) -> 0.13322435 | O73: =IF(COUNT(B73)=0,"",B73-('Signal Analysis'!$C$6+'Signal Analysis'!$C$5*H73)) -> 0.45223922
A74: 42432 | B74: 11.589792 | C74: 106.05 | D74: 107.15 | E74: 105.92 | F74: 107.13 | G74: 100.38388 | H74: 100.38388 | I74: =IF(COUNT(C74:F74)<4,"",IF(OR(D74<MAX(C74,F74)-0.000001,E74>MIN(C74,F74)+0.000001),"FAIL","OK")) -> OK | J74: =IF(COUNT(F74,G74)<2,"",G74/F74) -> 0.93702869 | K74: =H74/H73-1 -> 0.010469786 | L74: =H79/H74-1 -> -0.01120151 | M74: =IF(COUNT(B15:B74)<60,"",(B74-AVERAGE(B15:B74))/STDEV(B15:B74)) -> -0.30594668 | N74: =(H74-AVERAGE(H15:H74))/STDEV(H15:H74) -> 0.34075609 | O74: =IF(COUNT(B74)=0,"",B74-('Signal Analysis'!$C$6+'Signal Analysis'!$C$5*H74)) -> -0.34421317
... A457: 42986 | B457: 15.518587 | C457: 138.92999 | D457: 139.77 | E457: 138.61999 | F457: 139.11 | G457: 133.3212 | H457: 133.3212 | I457: =IF(COUNT(C457:F457)<4,"",IF(OR(D457<MAX(C457,F457)-0.000001,E457>MIN(C457,F457)+0.000001),"FAIL","OK")) -> OK | J457: =IF(COUNT(F457,G457)<2,"",G457/F457) -> 0.95838687 | K457: =H457/H456-1 -> 0 | L457: =H462/H457-1 -> 0.017611872 | M457: =IF(COUNT(B398:B457)<60,"",(B457-AVERAGE(B398:B457))/STDEV(B398:B457)) -> -1.0113964 | N457: =(H457-AVERAGE(H398:H457))/STDEV(H398:H457) -> -0.27547618 | O457: =IF(COUNT(B457)=0,"",B457-('Signal Analysis'!$C$6+'Signal Analysis'!$C$5*H457)) -> -0.92099295
A458: 42989 | B458: 15.838558 | C458: 140.39 | D458: 140.92 | E458: 140.23 | H458: 133.79081 | I458: =IF(COUNT(C458:F458)<4,"",IF(OR(D458<MAX(C458,F458)-0.000001,E458>MIN(C458,F458)+0.000001),"FAIL","OK")) | J458: =IF(COUNT(F458,G458)<2,"",G458/F458) | K458: =H458/H457-1 -> 0.0035223745 | L458: =H463/H458-1 -> 0.017550054 | M458: =IF(COUNT(B399:B458)<60,"",(B458-AVERAGE(B399:B458))/STDEV(B399:B458)) -> -0.34553322 | N458: =(H458-AVERAGE(H399:H458))/STDEV(H399:H458) -> -0.050772508 | O458: =IF(COUNT(B458)=0,"",B458-('Signal Analysis'!$C$6+'Signal Analysis'!$C$5*H458)) -> -0.66526078
A459: 42990 | B459: 15.518587 | C459: 141.03999 | D459: 141.69 | E459: 140.82001 | H459: 134.26041 | I459: =IF(COUNT(C459:F459)<4,"",IF(OR(D459<MAX(C459,F459)-0.000001,E459>MIN(C459,F459)+0.000001),"FAIL","OK")) | J459: =IF(COUNT(F459,G459)<2,"",G459/F459) | K459: =H459/H458-1 -> 0.0035100109 | L459: =H464/H459-1 -> 0.017488669 | M459: =IF(COUNT(B400:B459)<60,"",(B459-AVERAGE(B400:B459))/STDEV(B400:B459)) -> -0.96436417 | N459: =(H459-AVERAGE(H400:H459))/STDEV(H400:H459) -> 0.16757569 | O459: =IF(COUNT(B459)=0,"",B459-('Signal Analysis'!$C$6+'Signal Analysis'!$C$5*H459)) -> -1.0494704
A460: 42991 | B460: 16.158529 | C460: 141.41 | D460: 142.22 | E460: 141.32001 | H460: 134.73002 | I460: =IF(COUNT(C460:F460)<4,"",IF(OR(D460<MAX(C460,F460)-0.000001,E460>MIN(C460,F460)+0.000001),"FAIL","OK")) | J460: =IF(COUNT(F460,G460)<2,"",G460/F460) | K460: =H460/H459-1 -> 0.0034977338 | L460: =H465/H460-1 -> 0.017427711 | M460: =IF(COUNT(B401:B460)<60,"",(B460-AVERAGE(B401:B460))/STDEV(B401:B460)) -> 0.3148183 | N460: =(H460-AVERAGE(H401:H460))/STDEV(H401:H460) -> 0.39008583 | O460: =IF(COUNT(B460)=0,"",B460-('Signal Analysis'!$C$6+'Signal Analysis'!$C$5*H460)) -> -0.47376732
A461: 42992 | B461: 16.4785 | C461: 141.78 | D461: 142.16 | E461: 141.42 | H461: 135.19963 | I461: =IF(COUNT(C461:F461)<4,"",IF(OR(D461<MAX(C461,F461)-0.000001,E461>MIN(C461,F461)+0.000001),"FAIL","OK")) | J461: =IF(COUNT(F461,G461)<2,"",G461/F461) | K461: =H461/H460-1 -> 0.0034855423 | L461: =H466/H461-1 -> 0.017367177 | M461: =IF(COUNT(B402:B461)<60,"",(B461-AVERAGE(B402:B461))/STDEV(B402:B461)) -> 0.96263427 | N461: =(H461-AVERAGE(H402:H461))/STDEV(H402:H461) -> 0.59656109 | O461: =IF(COUNT(B461)=0,"",B461-('Signal Analysis'!$C$6+'Signal Analysis'!$C$5*H461)) -> -0.21803515
A462: 42993 | B462: 15.198617 | C462: 141.64 | D462: 142.47 | E462: 141.55 | H462: 135.66923 | I462: =IF(COUNT(C462:F462)<4,"",IF(OR(D462<MAX(C462,F462)-0.000001,E462>MIN(C462,F462)+0.000001),"FAIL","OK")) | J462: =IF(COUNT(F462,G462)<2,"",G462/F462) | K462: =H462/H461-1 -> 0.0034734355 | L462: =H467/H462-1 -> 0.017307062 | M462: =IF(COUNT(B403:B462)<60,"",(B462-AVERAGE(B403:B462))/STDEV(B403:B462)) -> -1.6417788 | N462: =(H462-AVERAGE(H403:H462))/STDEV(H403:H462) -> 0.79451286 | O462: =IF(COUNT(B462)=0,"",B462-('Signal Analysis'!$C$6+'Signal Analysis'!$C$5*H462)) -> -1.5621574
A463: 42996 | B463: 15.518587 | C463: 142.61999 | D463: 143.81 | E463: 142.60001 | H463: 136.13884 | I463: =IF(COUNT(C463:F463)<4,"",IF(OR(D463<MAX(C463,F463)-0.000001,E463>MIN(C463,F463)+0.000001),"FAIL","OK")) | J463: =IF(COUNT(F463,G463)<2,"",G463/F463) | K463: =H463/H462-1 -> 0.0034614125 | L463: =H468/H463-1 -> 0.017247362 | M463: =IF(COUNT(B404:B463)<60,"",(B463-AVERAGE(B404:B463))/STDEV(B404:B463)) -> -0.95964232 | N463: =(H463-AVERAGE(H404:H463))/STDEV(H404:H463) -> 0.9870624 | O463: =IF(COUNT(B463)=0,"",B463-('Signal Analysis'!$C$6+'Signal Analysis'!$C$5*H463)) -> -1.3064252
A464: 42997 | B464: 16.798471 | C464: 143.57001 | D464: 143.69 | E464: 143.09 | H464: 136.60845 | I464: =IF(COUNT(C464:F464)<4,"",IF(OR(D464<MAX(C464,F464)-0.000001,E464>MIN(C464,F464)+0.000001),"FAIL","OK")) | J464: =IF(COUNT(F464,G464)<2,"",G464/F464) | K464: =H464/H463-1 -> 0.0034494725 | L464: =H469/H464-1 -> 0.016978626 | M464: =IF(COUNT(B405:B464)<60,"",(B464-AVERAGE(B405:B464))/STDEV(B405:B464)) -> 1.6077046 | N464: =(H464-AVERAGE(H405:H464))/STDEV(H405:H464) -> 1.1755025 | O464: =IF(COUNT(B464)=0,"",B464-('Signal Analysis'!$C$6+'Signal Analysis'!$C$5*H464)) -> -0.090780394
A465: 42998 | B465: 15.953688 | C465: 143.53 | D465: 144.02 | E465: 143.26 | H465: 137.07806 | I465: =IF(COUNT(C465:F465)<4,"",IF(OR(D465<MAX(C465,F465)-0.000001,E465>MIN(C465,F465)+0.000001),"FAIL","OK")) | J465: =IF(COUNT(F465,G465)<2,"",G465/F465) | K465: =H465/H464-1 -> 0.0034376145 | L465: =H470/H465-1 -> 0.033328541 | M465: =IF(COUNT(B406:B465)<60,"",(B465-AVERAGE(B406:B465))/STDEV(B406:B465)) -> -0.083543454 | N465: =(H465-AVERAGE(H406:H465))/STDEV(H406:H465) -> 1.3520486 | O465: =IF(COUNT(B465)=0,"",B465-('Signal Analysis'!$C$6+'Signal Analysis'!$C$5*H465)) -> -0.99980182
A466: 42999 | B466: 16.004491 | C466: 144.02 | D466: 144.26 | E466: 143.48 | H466: 137.54766 | I466: =IF(COUNT(C466:F466)<4,"",IF(OR(D466<MAX(C466,F466)-0.000001,E466>MIN(C466,F466)+0.000001),"FAIL","OK")) | J466: =IF(COUNT(F466,G466)<2,"",G466/F466) | K466: =H466/H465-1 -> 0.0034258378 | L466: =H471/H466-1 -> 0.032524612 | M466: =IF(COUNT(B407:B466)<60,"",(B466-AVERAGE(B407:B466))/STDEV(B407:B466)) -> -0.004335707 | N466: =(H466-AVERAGE(H407:H466))/STDEV(H407:H466) -> 1.5049719 | O466: =IF(COUNT(B466)=0,"",B466-('Signal Analysis'!$C$6+'Signal Analysis'!$C$5*H466)) -> -1.0132379
A467: 43000 | B467: 16.9976 | C467: 143.67 | D467: 144.67 | E467: 143.56 | H467: 138.01727 | I467: =IF(COUNT(C467:F467)<4,"",IF(OR(D467<MAX(C467,F467)-0.000001,E467>MIN(C467,F467)+0.000001),"FAIL","OK")) | J467: =IF(COUNT(F467,G467)<2,"",G467/F467) | K467: =H467/H466-1 -> 0.0034141415 | L467: =H472/H467-1 -> 0.03144766 | M467: =IF(COUNT(B408:B467)<60,"",(B467-AVERAGE(B408:B467))/STDEV(B408:B467)) -> 1.9442792 | N467: =(H467-AVERAGE(H408:H467))/STDEV(H408:H467) -> 1.6594342 | O467: =IF(COUNT(B467)=0,"",B467-('Signal Analysis'!$C$6+'Signal Analysis'!$C$5*H467)) -> -0.084367422
A468: 43003 | B468: 17.042562 | C468: 144.27 | D468: 144.94 | E468: 143.69 | F468: 144.5 | G468: 138.48688 | H468: 138.48688 | I468: =IF(COUNT(C468:F468)<4,"",IF(OR(D468<MAX(C468,F468)-0.000001,E468>MIN(C468,F468)+0.000001),"FAIL","OK")) -> OK | J468: =IF(COUNT(F468,G468)<2,"",G468/F468) -> 0.95838669 | K468: =H468/H467-1 -> 0.0034025248 | L468: =H473/H468-1 -> 0.0405757 | M468: =IF(COUNT(B409:B468)<60,"",(B468-AVERAGE(B409:B468))/STDEV(B409:B468)) -> 1.9665101 | N468: =(H468-AVERAGE(H409:H468))/STDEV(H409:H468) -> 1.7858979 | O468: =IF(COUNT(B468)=0,"",B468-('Signal Analysis'!$C$6+'Signal Analysis'!$C$5*H468)) -> -0.10364453
A469: 43004 | B469: 17.766227 | C469: 144.28999 | D469: 145.14999 | E469: 144.17999 | F469: 144.61 | G469: 138.92787 | H469: 138.92787 | I469: =IF(COUNT(C469:F469)<4,"",IF(OR(D469<MAX(C469,F469)-0.000001,E469>MIN(C469,F469)+0.000001),"FAIL","OK")) -> OK | J469: =IF(COUNT(F469,G469)<2,"",G469/F469) -> 0.96070722 | K469: =H469/H468-1 -> 0.0031843811 | L469: =H474/H469-1 -> 0.039554727 | M469: =IF(COUNT(B410:B469)<60,"",(B469-AVERAGE(B410:B469))/STDEV(B410:B469)) -> 3.0630631 | N469: =(H469-AVERAGE(H410:H469))/STDEV(H410:H469) -> 1.881276 | O469: =IF(COUNT(B469)=0,"",B469-('Signal Analysis'!$C$6+'Signal Analysis'!$C$5*H469)) -> 0.55969629
A470: 43005 | B470: 17.638584 | C470: 145.63001 | D470: 147.86 | E470: 145.16 | F470: 147.44 | G470: 141.64667 | H470: 141.64667 | I470: =IF(COUNT(C470:F470)<4,"",IF(OR(D470<MAX(C470,F470)-0.000001,E470>MIN(C470,F470)+0.000001),"FAIL","OK")) -> OK | J470: =IF(COUNT(F470,G470)<2,"",G470/F470) -> 0.96070717 | K470: =H470/H469-1 -> 0.019569831 | L470: =H475/H470-1 -> 0.016345764 | M470: =IF(COUNT(B411:B470)<60,"",(B470-AVERAGE(B411:B470))/STDEV(B411:B470)) -> 2.6743433 | N470: =(H470-AVERAGE(H411:H470))/STDEV(H411:H470) -> 2.7614318 | O470: =IF(COUNT(B470)=0,"",B470-('Signal Analysis'!$C$6+'Signal Analysis'!$C$5*H470)) -> 0.060142556
A471: 43006 | B471: 17.157467 | C471: 147.25 | D471: 148.06 | E471: 146.78 | F471: 147.83 | G471: 142.02135 | H471: 142.02135 | I471: =IF(COUNT(C471:F471)<4,"",IF(OR(D471<MAX(C471,F471)-0.000001,E471>MIN(C471,F471)+0.000001),"FAIL","OK")) -> OK | J471: =IF(COUNT(F471,G471)<2,"",G471/F471) -> 0.9607072 | K471: =H471/H470-1 -> 0.0026451734 | L471: =H476/H471-1 -> 0.016437691 | M471: =IF(COUNT(B412:B471)<60,"",(B471-AVERAGE(B412:B471))/STDEV(B412:B471)) -> 1.7831004 | N471: =(H471-AVERAGE(H412:H471))/STDEV(H412:H471) -> 2.6796115 | O471: =IF(COUNT(B471)=0,"",B471-('Signal Analysis'!$C$6+'Signal Analysis'!$C$5*H471)) -> -0.47222753
A472: 43007 | B472: 18.139211 | C472: 147.92 | D472: 148.42999 | E472: 147.74 | F472: 148.17999 | G472: 142.35759 | H472: 142.35759 | I472: =IF(COUNT(C472:F472)<4,"",IF(OR(D472<MAX(C472,F472)-0.000001,E472>MIN(C472,F472)+0.000001),"FAIL","OK")) -> OK | J472: =IF(COUNT(F472,G472)<2,"",G472/F472) -> 0.96070723 | K472: =H472/H471-1 -> 0.0023675525 | L472: =H477/H472-1 -> 0.012619798 | M472: =IF(COUNT(B413:B472)<60,"",(B472-AVERAGE(B413:B472))/STDEV(B413:B472)) -> 3.0787612 | N472: =(H472-AVERAGE(H413:H472))/STDEV(H413:H472) -> 2.5873853 | O472: =IF(COUNT(B472)=0,"",B472-('Signal Analysis'!$C$6+'Signal Analysis'!$C$5*H472)) -> 0.46352034
A473: 43010 | B473: 18.01561 | C473: 148.31 | D473: 150 | E473: 148.08 | F473: 150 | G473: 144.10608 | H473: 144.10608 | I473: =IF(COUNT(C473:F473)<4,"",IF(OR(D473<MAX(C473,F473)-0.000001,E473>MIN(C473,F473)+0.000001),"FAIL","OK")) -> OK | J473: =IF(COUNT(F473,G473)<2,"",G473/F473) -> 0.96070719 | K473: =H473/H472-1 -> 0.012282373 | L473: =H478/H473-1 -> -0.0038000271 | M473: =IF(COUNT(B414:B473)<60,"",(B473-AVERAGE(B414:B473))/STDEV(B414:B473)) -> 2.6606153 | N473: =(H473-AVERAGE(H414:H473))/STDEV(H414:H473) -> 2.8917265 | O473: =IF(COUNT(B473)=0,"",B473-('Signal Analysis'!$C$6+'Signal Analysis'!$C$5*H473)) -> 0.10073963
A474: 43011 | B474: 16.952524 | C474: 150.11 | D474: 150.33 | E474: 149.33 | F474: 150.33 | G474: 144.42313 | H474: 144.42313 | I474: =IF(COUNT(C474:F474)<4,"",IF(OR(D474<MAX(C474,F474)-0.000001,E474>MIN(C474,F474)+0.000001),"FAIL","OK")) -> OK | J474: =IF(COUNT(F474,G474)<2,"",G474/F474) -> 0.96070727 | K474: =H474/H473-1 -> 0.0022000946 | L474: =H479/H474-1 -> -0.0031267015 | M474: =IF(COUNT(B415:B474)<60,"",(B474-AVERAGE(B415:B474))/STDEV(B415:B474)) -> 1.0930884 | N474: =(H474-AVERAGE(H415:H474))/STDEV(H415:H474) -> 2.7415896 | O474: =IF(COUNT(B474)=0,"",B474-('Signal Analysis'!$C$6+'Signal Analysis'!$C$5*H474)) -> -1.0057163
A475: 43012 | B475: 17.916097 | C475: 150.09 | D475: 150.61 | E475: 149.39 | F475: 149.85001 | G475: 143.96199 | H475: 143.96199 | I475: =IF(COUNT(C475:F475)<4,"",IF(OR(D475<MAX(C475,F475)-0.000001,E475>MIN(C475,F475)+0.000001),"FAIL","OK")) -> OK | J475: =IF(COUNT(F475,G475)<2,"",G475/F475) -> 0.96070727 | K475: =H475/H474-1 -> -0.0031929512 | L475: =H480/H475-1 -> -0.00066742617 | M475: =IF(COUNT(B416:B475)<60,"",(B475-AVERAGE(B416:B475))/STDEV(B416:B475)) -> 2.358754 | N475: =(H475-AVERAGE(H416:H475))/STDEV(H416:H475) -> 2.4275919 | O475: =IF(COUNT(B475)=0,"",B475-('Signal Analysis'!$C$6+'Signal Analysis'!$C$5*H475)) -> 0.020937138
A476: 43013 | B476: 16.585523 | C476: 150.28999 | D476: 150.63001 | E476: 149.86999 | F476: 150.26 | G476: 144.35585 | H476: 144.35585 | I476: =IF(COUNT(C476:F476)<4,"",IF(OR(D476<MAX(C476,F476)-0.000001,E476>MIN(C476,F476)+0.000001),"FAIL","OK")) -> OK | J476: =IF(COUNT(F476,G476)<2,"",G476/F476) -> 0.96070714 | K476: =H476/H475-1 -> 0.002735861 | L476: =H481/H476-1 -> -0.0041262062 | M476: =IF(COUNT(B417:B476)<60,"",(B476-AVERAGE(B417:B476))/STDEV(B417:B476)) -> 0.50714037 | N476: =(H476-AVERAGE(H417:H476))/STDEV(H417:H476) -> 2.371814 | O476: =IF(COUNT(B476)=0,"",B476-('Signal Analysis'!$C$6+'Signal Analysis'!$C$5*H476)) -> -1.3635138
A477: 43014 | B477: 17.954465 | C477: 149.71001 | D477: 150.34 | E477: 149.57001 | F477: 150.05 | G477: 144.15411 | H477: 144.15411 | I477: =IF(COUNT(C477:F477)<4,"",IF(OR(D477<MAX(C477,F477)-0.000001,E477>MIN(C477,F477)+0.000001),"FAIL","OK")) -> OK | J477: =IF(COUNT(F477,G477)<2,"",G477/F477) -> 0.96070717 | K477: =H477/H476-1 -> -0.001397491 | L477: =H482/H477-1 -> -0.0045316778 | M477: =IF(COUNT(B418:B477)<60,"",(B477-AVERAGE(B418:B477))/STDEV(B418:B477)) -> 2.2720124 | N477: =(H477-AVERAGE(H418:H477))/STDEV(H418:H477) -> 2.1853383 | O477: =IF(COUNT(B477)=0,"",B477-('Signal Analysis'!$C$6+'Signal Analysis'!$C$5*H477)) -> 0.033023793
A478: 43017 | B478: 17.768762 | C478: 150.19 | D478: 150.67999 | E478: 149.17999 | F478: 149.42999 | G478: 143.55847 | H478: 143.55847 | I478: =IF(COUNT(C478:F478)<4,"",IF(OR(D478<MAX(C478,F478)-0.000001,E478>MIN(C478,F478)+0.000001),"FAIL","OK")) -> OK | J478: =IF(COUNT(F478,G478)<2,"",G478/F478) -> 0.96070721 | K478: =H478/H477-1 -> -0.0041319806 | L478: =H483/H478-1 -> -0.0012716491 | M478: =IF(COUNT(B419:B478)<60,"",(B478-AVERAGE(B419:B478))/STDEV(B419:B478)) -> 1.9255441 | N478: =(H478-AVERAGE(H419:H478))/STDEV(H419:H478) -> 1.9368872 | O478: =IF(COUNT(B478)=0,"",B478-('Signal Analysis'!$C$6+'Signal Analysis'!$C$5*H478)) -> -0.071200252
A479: 43018 | B479: 17.564505 | C479: 149.92999 | D479: 150.28999 | E479: 149.41 | F479: 149.86 | G479: 143.97156 | H479: 143.97156 | I479: =IF(COUNT(C479:F479)<4,"",IF(OR(D479<MAX(C479,F479)-0.000001,E479>MIN(C479,F479)+0.000001),"FAIL","OK")) -> OK | J479: =IF(COUNT(F479,G479)<2,"",G479/F479) -> 0.96070704 | K479: =H479/H478-1 -> 0.0028774756 | L479: =H484/H479-1 -> -0.0070065506 | M479: =IF(COUNT(B420:B479)<60,"",(B479-AVERAGE(B420:B479))/STDEV(B420:B479)) -> 1.6032854 | N479: =(H479-AVERAGE(H420:H479))/STDEV(H420:H479) -> 1.9399898 | O479: =IF(COUNT(B479)=0,"",B479-('Signal Analysis'!$C$6+'Signal Analysis'!$C$5*H479)) -> -0.33196447
... A753: 43413 | B753: 19.074848 | C753: 156 | D753: 156.03 | E753: 152.95 | F753: 154.08 | G753: 149.86568 | H753: 149.86568 | I753: =IF(COUNT(C753:F753)<4,"",IF(OR(D753<MAX(C753,F753)-0.000001,E753>MIN(C753,F753)+0.000001),"FAIL","OK")) -> OK | J753: =IF(COUNT(F753,G753)<2,"",G753/F753) -> 0.97264846 | K753: =H753/H752-1 -> -0.018536257 | L753: =H758/H753-1 -> -0.028232087 | M753: =IF(COUNT(B694:B753)<60,"",(B753-AVERAGE(B694:B753))/STDEV(B694:B753)) -> -0.47500097 | N753: =(H753-AVERAGE(H694:H753))/STDEV(H694:H753) -> -1.047033 | O753: =IF(COUNT(B753)=0,"",B753-('Signal Analysis'!$C$6+'Signal Analysis'!$C$5*H753)) -> 0.37210812
A754: 43416 | H754: 149.01947 | I754: =IF(COUNT(C754:F754)<4,"",IF(OR(D754<MAX(C754,F754)-0.000001,E754>MIN(C754,F754)+0.000001),"FAIL","OK")) | J754: =IF(COUNT(F754,G754)<2,"",G754/F754) | K754: =H754/H753-1 -> -0.0056464174 | L754: =H759/H754-1 -> -0.028392402 | M754: =IF(COUNT(B695:B754)<60,"",(B754-AVERAGE(B695:B754))/STDEV(B695:B754)) | N754: =(H754-AVERAGE(H695:H754))/STDEV(H695:H754) -> -1.1126497 | O754: =IF(COUNT(B754)=0,"",B754-('Signal Analysis'!$C$6+'Signal Analysis'!$C$5*H754))
A755: 43417 | H755: 148.17327 | I755: =IF(COUNT(C755:F755)<4,"",IF(OR(D755<MAX(C755,F755)-0.000001,E755>MIN(C755,F755)+0.000001),"FAIL","OK")) | J755: =IF(COUNT(F755,G755)<2,"",G755/F755) | K755: =H755/H754-1 -> -0.0056784805 | L755: =H760/H755-1 -> -0.041683097 | M755: =IF(COUNT(B696:B755)<60,"",(B755-AVERAGE(B696:B755))/STDEV(B696:B755)) | N755: =(H755-AVERAGE(H696:H755))/STDEV(H696:H755) -> -1.1741576 | O755: =IF(COUNT(B755)=0,"",B755-('Signal Analysis'!$C$6+'Signal Analysis'!$C$5*H755))
A756: 43418 | H756: 147.32706 | I756: =IF(COUNT(C756:F756)<4,"",IF(OR(D756<MAX(C756,F756)-0.000001,E756>MIN(C756,F756)+0.000001),"FAIL","OK")) | J756: =IF(COUNT(F756,G756)<2,"",G756/F756) | K756: =H756/H755-1 -> -0.0057109098 | L756: =H761/H756-1 -> -0.022710651 | M756: =IF(COUNT(B697:B756)<60,"",(B756-AVERAGE(B697:B756))/STDEV(B697:B756)) | N756: =(H756-AVERAGE(H697:H756))/STDEV(H697:H756) -> -1.2319954 | O756: =IF(COUNT(B756)=0,"",B756-('Signal Analysis'!$C$6+'Signal Analysis'!$C$5*H756))
A757: 43419 | H757: 146.48086 | I757: =IF(COUNT(C757:F757)<4,"",IF(OR(D757<MAX(C757,F757)-0.000001,E757>MIN(C757,F757)+0.000001),"FAIL","OK")) | J757: =IF(COUNT(F757,G757)<2,"",G757/F757) | K757: =H757/H756-1 -> -0.0057437116 | L757: =H762/H757-1 -> -0.01799477 | M757: =IF(COUNT(B698:B757)<60,"",(B757-AVERAGE(B698:B757))/STDEV(B698:B757)) | N757: =(H757-AVERAGE(H698:H757))/STDEV(H698:H757) -> -1.2868072 | O757: =IF(COUNT(B757)=0,"",B757-('Signal Analysis'!$C$6+'Signal Analysis'!$C$5*H757))
A758: 43420 | H758: 145.63466 | I758: =IF(COUNT(C758:F758)<4,"",IF(OR(D758<MAX(C758,F758)-0.000001,E758>MIN(C758,F758)+0.000001),"FAIL","OK")) | J758: =IF(COUNT(F758,G758)<2,"",G758/F758) | K758: =H758/H757-1 -> -0.0057768924 | L758: =H763/H758-1 -> 0.00053426043 | M758: =IF(COUNT(B699:B758)<60,"",(B758-AVERAGE(B699:B758))/STDEV(B699:B758)) | N758: =(H758-AVERAGE(H699:H758))/STDEV(H699:H758) -> -1.3380598 | O758: =IF(COUNT(B758)=0,"",B758-('Signal Analysis'!$C$6+'Signal Analysis'!$C$5*H758))
A759: 43423 | B759: 17.76912 | C759: 151.67999 | D759: 152.03 | E759: 148.36999 | F759: 148.86 | G759: 144.78845 | H759: 144.78845 | I759: =IF(COUNT(C759:F759)<4,"",IF(OR(D759<MAX(C759,F759)-0.000001,E759>MIN(C759,F759)+0.000001),"FAIL","OK")) -> OK | J759: =IF(COUNT(F759,G759)<2,"",G759/F759) -> 0.97264847 | K759: =H759/H758-1 -> -0.0058104588 | L759: =H764/H759-1 -> -0.0019478625 | M759: =IF(COUNT(B700:B759)<60,"",(B759-AVERAGE(B700:B759))/STDEV(B700:B759)) | N759: =(H759-AVERAGE(H700:H759))/STDEV(H700:H759) -> -1.3869726 | O759: =IF(COUNT(B759)=0,"",B759-('Signal Analysis'!$C$6+'Signal Analysis'!$C$5*H759)) -> -0.23909343
A760: 43424 | B760: 18.075691 | C760: 147.25 | D760: 148.42999 | E760: 145.59 | F760: 145.99 | G760: 141.99695 | H760: 141.99695 | I760: =IF(COUNT(C760:F760)<4,"",IF(OR(D760<MAX(C760,F760)-0.000001,E760>MIN(C760,F760)+0.000001),"FAIL","OK")) -> OK | J760: =IF(COUNT(F760,G760)<2,"",G760/F760) -> 0.97264842 | K760: =H760/H759-1 -> -0.01927988 | L760: =H765/H760-1 -> 0.042811174 | M760: =IF(COUNT(B701:B760)<60,"",(B760-AVERAGE(B701:B760))/STDEV(B701:B760)) | N760: =(H760-AVERAGE(H701:H760))/STDEV(H701:H760) -> -1.6465754 | O760: =IF(COUNT(B760)=0,"",B760-('Signal Analysis'!$C$6+'Signal Analysis'!$C$5*H760)) -> 0.44933394
A761: 43425 | B761: 18.70415 | C761: 146.78 | D761: 149.36999 | E761: 146.53 | F761: 148.03 | G761: 143.98117 | H761: 143.98117 | I761: =IF(COUNT(C761:F761)<4,"",IF(OR(D761<MAX(C761,F761)-0.000001,E761>MIN(C761,F761)+0.000001),"FAIL","OK")) -> OK | J761: =IF(COUNT(F761,G761)<2,"",G761/F761) -> 0.9726486 | K761: =H761/H760-1 -> 0.013973702 | L761: =H766/H761-1 -> 0.025670336 | M761: =IF(COUNT(B702:B761)<60,"",(B761-AVERAGE(B702:B761))/STDEV(B702:B761)) | N761: =(H761-AVERAGE(H702:H761))/STDEV(H702:H761) -> -1.3682018 | O761: =IF(COUNT(B761)=0,"",B761-('Signal Analysis'!$C$6+'Signal Analysis'!$C$5*H761)) -> 0.80636577
A762: 43427 | B762: 18.883075 | C762: 146.82001 | D762: 149.3 | E762: 146.81 | F762: 147.89 | G762: 143.84497 | H762: 143.84497 | I762: =IF(COUNT(C762:F762)<4,"",IF(OR(D762<MAX(C762,F762)-0.000001,E762>MIN(C762,F762)+0.000001),"FAIL","OK")) -> OK | J762: =IF(COUNT(F762,G762)<2,"",G762/F762) -> 0.9726484 | K762: =H762/H761-1 -> -0.00094595702 | L762: =H767/H762-1 -> 0.031983475 | M762: =IF(COUNT(B703:B762)<60,"",(B762-AVERAGE(B703:B762))/STDEV(B703:B762)) | N762: =(H762-AVERAGE(H703:H762))/STDEV(H703:H762) -> -1.3384389 | O762: =IF(COUNT(B762)=0,"",B762-('Signal Analysis'!$C$6+'Signal Analysis'!$C$5*H762)) -> 1.0039224
A763: 43430 | B763: 17.734761 | C763: 149.32001 | D763: 150.39999 | E763: 148.74 | F763: 149.81 | G763: 145.71246 | H763: 145.71246 | I763: =IF(COUNT(C763:F763)<4,"",IF(OR(D763<MAX(C763,F763)-0.000001,E763>MIN(C763,F763)+0.000001),"FAIL","OK")) -> OK | J763: =IF(COUNT(F763,G763)<2,"",G763/F763) -> 0.97264845 | K763: =H763/H762-1 -> 0.012982671 | L763: =H768/H763-1 -> 0.028502806 | M763: =IF(COUNT(B704:B763)<60,"",(B763-AVERAGE(B704:B763))/STDEV(B704:B763)) | N763: =(H763-AVERAGE(H704:H763))/STDEV(H704:H763) -> -1.0877445 | O763: =IF(COUNT(B763)=0,"",B763-('Signal Analysis'!$C$6+'Signal Analysis'!$C$5*H763)) -> -0.39985042
A764: 43431 | B764: 18.383525 | C764: 149.17999 | D764: 149.73 | E764: 148.28999 | F764: 148.57001 | G764: 144.50642 | H764: 144.50642 | I764: =IF(COUNT(C764:F764)<4,"",IF(OR(D764<MAX(C764,F764)-0.000001,E764>MIN(C764,F764)+0.000001),"FAIL","OK")) -> OK | J764: =IF(COUNT(F764,G764)<2,"",G764/F764) -> 0.9726487 | K764: =H764/H763-1 -> -0.0082768418 | L764: =H769/H764-1 -> -0.0070675128 | M764: =IF(COUNT(B705:B764)<60,"",(B764-AVERAGE(B705:B764))/STDEV(B705:B764)) | N764: =(H764-AVERAGE(H705:H764))/STDEV(H705:H764) -> -1.1927793 | O764: =IF(COUNT(B764)=0,"",B764-('Signal Analysis'!$C$6+'Signal Analysis'!$C$5*H764)) -> 0.41389081
A765: 43432 | B765: 18.490673 | C765: 149.2 | D765: 152.36999 | E765: 147.7 | F765: 152.24 | G765: 148.076 | H765: 148.076 | I765: =IF(COUNT(C765:F765)<4,"",IF(OR(D765<MAX(C765,F765)-0.000001,E765>MIN(C765,F765)+0.000001),"FAIL","OK")) -> OK | J765: =IF(COUNT(F765,G765)<2,"",G765/F765) -> 0.97264844 | K765: =H765/H764-1 -> 0.024701878 | L765: =H770/H765-1 -> -0.033105499 | M765: =IF(COUNT(B706:B765)<60,"",(B765-AVERAGE(B706:B765))/STDEV(B706:B765)) | N765: =(H765-AVERAGE(H706:H765))/STDEV(H706:H765) -> -0.74687739 | O765: =IF(COUNT(B765)=0,"",B765-('Signal Analysis'!$C$6+'Signal Analysis'!$C$5*H765)) -> 0.032746862
A766: 43433 | B766: 16.76068 | C766: 151.61 | D766: 152.74 | E766: 150.44 | F766: 151.83 | G766: 147.67722 | H766: 147.67722 | I766: =IF(COUNT(C766:F766)<4,"",IF(OR(D766<MAX(C766,F766)-0.000001,E766>MIN(C766,F766)+0.000001),"FAIL","OK")) -> OK | J766: =IF(COUNT(F766,G766)<2,"",G766/F766) -> 0.97264845 | K766: =H766/H765-1 -> -0.0026931305 | L766: =H771/H766-1 -> -0.051438944 | M766: =IF(COUNT(B707:B766)<60,"",(B766-AVERAGE(B707:B766))/STDEV(B707:B766)) | N766: =(H766-AVERAGE(H707:H766))/STDEV(H707:H766) -> -0.76715173 | O766: =IF(COUNT(B766)=0,"",B766-('Signal Analysis'!$C$6+'Signal Analysis'!$C$5*H766)) -> -1.642695
A767: 43434 | B767: 17.58033 | C767: 151.46001 | D767: 152.86 | E767: 151.08 | F767: 152.61999 | G767: 148.44563 | H767: 148.44563 | I767: =IF(COUNT(C767:F767)<4,"",IF(OR(D767<MAX(C767,F767)-0.000001,E767>MIN(C767,F767)+0.000001),"FAIL","OK")) -> OK | J767: =IF(COUNT(F767,G767)<2,"",G767/F767) -> 0.97264866 | K767: =H767/H766-1 -> 0.0052033551 | L767: =H772/H767-1 -> -0.059101099 | M767: =IF(COUNT(B708:B767)<60,"",(B767-AVERAGE(B708:B767))/STDEV(B708:B767)) | N767: =(H767-AVERAGE(H708:H767))/STDEV(H708:H767) -> -0.64860423 | O767: =IF(COUNT(B767)=0,"",B767-('Signal Analysis'!$C$6+'Signal Analysis'!$C$5*H767)) -> -0.92815865
A768: 43437 | B768: 18.593385 | C768: 154.39 | D768: 154.48 | E768: 152.02 | F768: 154.08 | G768: 149.86568 | H768: 149.86568 | I768: =IF(COUNT(C768:F768)<4,"",IF(OR(D768<MAX(C768,F768)-0.000001,E768>MIN(C768,F768)+0.000001),"FAIL","OK")) -> OK | J768: =IF(COUNT(F768,G768)<2,"",G768/F768) -> 0.97264846 | K768: =H768/H767-1 -> 0.0095660881 | L768: =H773/H768-1 -> -0.068990106 | M768: =IF(COUNT(B709:B768)<60,"",(B768-AVERAGE(B709:B768))/STDEV(B709:B768)) | N768: =(H768-AVERAGE(H709:H768))/STDEV(H709:H768) -> -0.45049038 | O768: =IF(COUNT(B768)=0,"",B768-('Signal Analysis'!$C$6+'Signal Analysis'!$C$5*H768)) -> -0.10935475
A769: 43438 | B769: 16.663803 | C769: 153.75 | D769: 154.13001 | E769: 147.14 | F769: 147.52 | G769: 143.48512 | H769: 143.48512 | I769: =IF(COUNT(C769:F769)<4,"",IF(OR(D769<MAX(C769,F769)-0.000001,E769>MIN(C769,F769)+0.000001),"FAIL","OK")) -> OK | J769: =IF(COUNT(F769,G769)<2,"",G769/F769) -> 0.97264858 | K769: =H769/H768-1 -> -0.042575152 | L769: =H774/H769-1 -> -0.018302559 | M769: =IF(COUNT(B710:B769)<60,"",(B769-AVERAGE(B710:B769))/STDEV(B710:B769)) | N769: =(H769-AVERAGE(H710:H769))/STDEV(H710:H769) -> -1.2061753 | O769: =IF(COUNT(B769)=0,"",B769-('Signal Analysis'!$C$6+'Signal Analysis'!$C$5*H769)) -> -1.1661259
A770: 43440 | B770: 16.904044 | C770: 145.45 | D770: 147.2 | E770: 143.42999 | F770: 147.2 | G770: 143.17387 | H770: 143.17387 | I770: =IF(COUNT(C770:F770)<4,"",IF(OR(D770<MAX(C770,F770)-0.000001,E770>MIN(C770,F770)+0.000001),"FAIL","OK")) -> OK | J770: =IF(COUNT(F770,G770)<2,"",G770/F770) -> 0.97264862 | K770: =H770/H769-1 -> -0.0021692075 | L770: =H775/H770-1 -> -0.030095246 | M770: =IF(COUNT(B711:B770)<60,"",(B770-AVERAGE(B711:B770))/STDEV(B711:B770)) | N770: =(H770-AVERAGE(H711:H770))/STDEV(H711:H770) -> -1.2095142 | O770: =IF(COUNT(B770)=0,"",B770-('Signal Analysis'!$C$6+'Signal Analysis'!$C$5*H770)) -> -0.88330738
... A1035: 43825 | B1035: 20.016643 | C1035: 166.83 | D1035: 166.98 | E1035: 166.36 | F1035: 166.67999 | G1035: 164.85005 | H1035: 164.85005 | I1035: =IF(COUNT(C1035:F1035)<4,"",IF(OR(D1035<MAX(C1035,F1035)-0.000001,E1035>MIN(C1035,F1035)+0.000001),"FAIL","OK")) -> OK | J1035: =IF(COUNT(F1035,G1035)<2,"",G1035/F1035) -> 0.98902123 | K1035: =H1035/H1034-1 -> 0 | L1035: =H1040/H1035-1 -> -0.0092991114 | M1035: =IF(COUNT(B976:B1035)<60,"",(B1035-AVERAGE(B976:B1035))/STDEV(B976:B1035)) -> 0.28768916 | N1035: =(H1035-AVERAGE(H976:H1035))/STDEV(H976:H1035) -> 1.6641695 | O1035: =IF(COUNT(B1035)=0,"",B1035-('Signal Analysis'!$C$6+'Signal Analysis'!$C$5*H1035)) -> -0.73584552
A1036: 43826 | C1036: 167.11999 | D1036: 167.11999 | E1036: 165.42999 | F1036: 165.86 | G1036: 164.03906 | H1036: 164.03906 | I1036: =IF(COUNT(C1036:F1036)<4,"",IF(OR(D1036<MAX(C1036,F1036)-0.000001,E1036>MIN(C1036,F1036)+0.000001),"FAIL","OK")) -> OK | J1036: =IF(COUNT(F1036,G1036)<2,"",G1036/F1036) -> 0.98902123 | K1036: =H1036/H1035-1 -> -0.0049195556 | L1036: =H1041/H1036-1 -> -0.0030748469 | M1036: =IF(COUNT(B977:B1036)<60,"",(B1036-AVERAGE(B977:B1036))/STDEV(B977:B1036)) | N1036: =(H1036-AVERAGE(H977:H1036))/STDEV(H977:H1036) -> 1.4798657 | O1036: =IF(COUNT(B1036)=0,"",B1036-('Signal Analysis'!$C$6+'Signal Analysis'!$C$5*H1036))
A1037: 43829 | C1037: 165.98 | D1037: 166.21001 | E1037: 164.57001 | F1037: 165.44 | G1037: 163.62369 | H1037: 163.62369 | I1037: =IF(COUNT(C1037:F1037)<4,"",IF(OR(D1037<MAX(C1037,F1037)-0.000001,E1037>MIN(C1037,F1037)+0.000001),"FAIL","OK")) -> OK | J1037: =IF(COUNT(F1037,G1037)<2,"",G1037/F1037) -> 0.98902131 | K1037: =H1037/H1036-1 -> -0.0025321713 | M1037: =IF(COUNT(B978:B1037)<60,"",(B1037-AVERAGE(B978:B1037))/STDEV(B978:B1037)) | N1037: =(H1037-AVERAGE(H978:H1037))/STDEV(H978:H1037) -> 1.3698875 | O1037: =IF(COUNT(B1037)=0,"",B1037-('Signal Analysis'!$C$6+'Signal Analysis'!$C$5*H1037))
A1038: 43830 | C1038: 165.08 | D1038: 166.35001 | E1038: 164.71001 | F1038: 165.67 | G1038: 163.85113 | H1038: 163.85113 | I1038: =IF(COUNT(C1038:F1038)<4,"",IF(OR(D1038<MAX(C1038,F1038)-0.000001,E1038>MIN(C1038,F1038)+0.000001),"FAIL","OK")) -> OK | J1038: =IF(COUNT(F1038,G1038)<2,"",G1038/F1038) -> 0.98902117 | K1038: =H1038/H1037-1 -> 0.0013900616 | M1038: =IF(COUNT(B979:B1038)<60,"",(B1038-AVERAGE(B979:B1038))/STDEV(B979:B1038)) | N1038: =(H1038-AVERAGE(H979:H1038))/STDEV(H979:H1038) -> 1.372652 | O1038: =IF(COUNT(B1038)=0,"",B1038-('Signal Analysis'!$C$6+'Signal Analysis'!$C$5*H1038))
A1039: 43832 | C1039: 166.74 | D1039: 166.75 | E1039: 164.23 | F1039: 165.78 | G1039: 163.95995 | H1039: 163.95995 | I1039: =IF(COUNT(C1039:F1039)<4,"",IF(OR(D1039<MAX(C1039,F1039)-0.000001,E1039>MIN(C1039,F1039)+0.000001),"FAIL","OK")) -> OK | J1039: =IF(COUNT(F1039,G1039)<2,"",G1039/F1039) -> 0.98902128 | K1039: =H1039/H1038-1 -> 0.00066408451 | M1039: =IF(COUNT(B980:B1039)<60,"",(B1039-AVERAGE(B980:B1039))/STDEV(B980:B1039)) | N1039: =(H1039-AVERAGE(H980:H1039))/STDEV(H980:H1039) -> 1.3574376 | O1039: =IF(COUNT(B1039)=0,"",B1039-('Signal Analysis'!$C$6+'Signal Analysis'!$C$5*H1039))
A1040: 43833 | C1040: 163.74 | D1040: 165.41 | E1040: 163.7 | F1040: 165.13001 | G1040: 163.31709 | H1040: 163.31709 | I1040: =IF(COUNT(C1040:F1040)<4,"",IF(OR(D1040<MAX(C1040,F1040)-0.000001,E1040>MIN(C1040,F1040)+0.000001),"FAIL","OK")) -> OK | J1040: =IF(COUNT(F1040,G1040)<2,"",G1040/F1040) -> 0.9890213 | K1040: =H1040/H1039-1 -> -0.0039207929 | M1040: =IF(COUNT(B981:B1040)<60,"",(B1040-AVERAGE(B981:B1040))/STDEV(B981:B1040)) | N1040: =(H1040-AVERAGE(H981:H1040))/STDEV(H981:H1040) -> 1.2206694 | O1040: =IF(COUNT(B1040)=0,"",B1040-('Signal Analysis'!$C$6+'Signal Analysis'!$C$5*H1040))
A1041: 43836 | C1041: 163.85001 | D1041: 165.53999 | E1041: 163.53999 | F1041: 165.35001 | G1041: 163.53467 | H1041: 163.53467 | I1041: =IF(COUNT(C1041:F1041)<4,"",IF(OR(D1041<MAX(C1041,F1041)-0.000001,E1041>MIN(C1041,F1041)+0.000001),"FAIL","OK")) -> OK | J1041: =IF(COUNT(F1041,G1041)<2,"",G1041/F1041) -> 0.98902124 | K1041: =H1041/H1040-1 -> 0.0013322243 | M1041: =IF(COUNT(B982:B1041)<60,"",(B1041-AVERAGE(B982:B1041))/STDEV(B982:B1041)) | N1041: =(H1041-AVERAGE(H982:H1041))/STDEV(H982:H1041) -> 1.2488155 | O1041: =IF(COUNT(B1041)=0,"",B1041-('Signal Analysis'!$C$6+'Signal Analysis'!$C$5*H1041))

Sheet Signal Analysis
A1: Signal efficacy — all figures computed live from the Data (Cleaned) sheet
A3: 1. What is the Signal actually made of?
A4: Regression Signal = intercept + slope x Adj Close (same day)
B5: Slope | C5: =SLOPE('Data (Cleaned)'!$B$4:$B$1041,'Data (Cleaned)'!$H$4:$H$1041) -> 0.13679243
B6: Intercept | C6: =INTERCEPT('Data (Cleaned)'!$B$4:$B$1041,'Data (Cleaned)'!$H$4:$H$1041) -> -1.7977499
B7: R-squared | C7: =RSQ('Data (Cleaned)'!$B$4:$B$1041,'Data (Cleaned)'!$H$4:$H$1041) -> 0.87893878
B8: Implied price per 1.0 of Signal | C8: =1/C5 -> 7.3103462
B9: Read: 88% of the Signal is just the ETF price rescaled by ~1/8.1. It is not independent information.
A11: 2. Where in time does the Signal's information sit?
A12: Correlation of the Signal residual (Signal net of today's price) with the ETF return k days away.
A13: k < 0 = past (knowable), k = 0 = today, k > 0 = FUTURE (not knowable at forecast time).
B14: k | C14: corr(residual, return t+k) | D14: knowable at time t?
B15: -6 | C15: =IFERROR(CORREL(OFFSET('Data (Cleaned)'!$O$10,0,0,1032,1),OFFSET('Data (Cleaned)'!$K$4,0,0,1032,1)),"") -> -0.048757515 | D15: yes
B16: -5 | C16: =IFERROR(CORREL(OFFSET('Data (Cleaned)'!$O$9,0,0,1033,1),OFFSET('Data (Cleaned)'!$K$4,0,0,1033,1)),"") -> -0.023454611 | D16: yes
B17: -4 | C17: =IFERROR(CORREL(OFFSET('Data (Cleaned)'!$O$8,0,0,1034,1),OFFSET('Data (Cleaned)'!$K$4,0,0,1034,1)),"") -> -0.056303727 | D17: yes
B18: -3 | C18: =IFERROR(CORREL(OFFSET('Data (Cleaned)'!$O$7,0,0,1035,1),OFFSET('Data (Cleaned)'!$K$4,0,0,1035,1)),"") -> -0.0059522677 | D18: yes
B19: -2 | C19: =IFERROR(CORREL(OFFSET('Data (Cleaned)'!$O$6,0,0,1036,1),OFFSET('Data (Cleaned)'!$K$4,0,0,1036,1)),"") -> -0.018589523 | D19: yes
B20: -1 | C20: =IFERROR(CORREL(OFFSET('Data (Cleaned)'!$O$5,0,0,1037,1),OFFSET('Data (Cleaned)'!$K$4,0,0,1037,1)),"") -> -0.015554268 | D20: yes
B21: 0 | C21: =IFERROR(CORREL(OFFSET('Data (Cleaned)'!$O$4,0,0,1038,1),OFFSET('Data (Cleaned)'!$K$4,0,0,1038,1)),"") -> -0.019871592 | D21: yes
B22: 1 | C22: =IFERROR(CORREL(OFFSET('Data (Cleaned)'!$O$4,0,0,1037,1),OFFSET('Data (Cleaned)'!$K$5,0,0,1037,1)),"") -> 0.15621082 | D22: NO — future
B23: 2 | C23: =IFERROR(CORREL(OFFSET('Data (Cleaned)'!$O$4,0,0,1036,1),OFFSET('Data (Cleaned)'!$K$6,0,0,1036,1)),"") -> 0.17913678 | D23: NO — future
B24: 3 | C24: =IFERROR(CORREL(OFFSET('Data (Cleaned)'!$O$4,0,0,1035,1),OFFSET('Data (Cleaned)'!$K$7,0,0,1035,1)),"") -> 0.19939017 | D24: NO — future
B25: 4 | C25: =IFERROR(CORREL(OFFSET('Data (Cleaned)'!$O$4,0,0,1034,1),OFFSET('Data (Cleaned)'!$K$8,0,0,1034,1)),"") -> 0.12376621 | D25: NO — future
B26: 5 | C26: =IFERROR(CORREL(OFFSET('Data (Cleaned)'!$O$4,0,0,1033,1),OFFSET('Data (Cleaned)'!$K$9,0,0,1033,1)),"") -> 0.14489654 | D26: NO — future
B27: 6 | C27: =IFERROR(CORREL(OFFSET('Data (Cleaned)'!$O$4,0,0,1032,1),OFFSET('Data (Cleaned)'!$K$10,0,0,1032,1)),"") -> 0.12856923 | D27: NO — future
B28: 7 | C28: =IFERROR(CORREL(OFFSET('Data (Cleaned)'!$O$4,0,0,1031,1),OFFSET('Data (Cleaned)'!$K$11,0,0,1031,1)),"") -> 0.0016967556 | D28: NO — future
B29: 8 | C29: =IFERROR(CORREL(OFFSET('Data (Cleaned)'!$O$4,0,0,1030,1),OFFSET('Data (Cleaned)'!$K$12,0,0,1030,1)),"") -> 0.017629069 | D29: NO — future
B30: Read: the residual is uncorrelated with everything up to today, jumps to +0.13/+0.20 for the next six sessions,
B31: then collapses to zero. That is the fingerprint of a signal computed from prices 3-7 days ahead.
A33: 3. Apparent predictive power (and why it is not real)
B34: Metric | C34: Value | D34: Interpretation
B35: R-squared, Signal ~ Adj Close 6 days later | C35: =RSQ(OFFSET('Data (Cleaned)'!$B$4,0,0,1032,1),OFFSET('Data (Cleaned)'!$H$10,0,0,1032,1)) -> 0.89593916 | D35: Higher than the same-day fit (see above) — the Signal tracks a future price better than today's
B36: IC, Signal z-score vs next 5d return | C36: =CORREL('Data (Cleaned)'!$M$4:$M$1041,'Data (Cleaned)'!$L$4:$L$1041) -> 0.22591621 | D36: An information coefficient of this size is not achievable on a liquid ETF
B37: IC, price z-score vs next 5d return (benchmark) | C37: =CORREL('Data (Cleaned)'!$N$4:$N$1041,'Data (Cleaned)'!$L$4:$L$1041) -> -0.11211326 | D37: Price momentum alone over the same window — the honest comparison
B38: IC, Signal residual vs next 5d return | C38: =CORREL('Data (Cleaned)'!$O$4:$O$1041,'Data (Cleaned)'!$L$4:$L$1041) -> 0.35044038 | D38: The "proprietary" part is where all the apparent skill sits
A40: 4. Backtest (long when Signal z-score > 0, else flat; next-day execution; no costs)
B41: Strategy | C41: Ann. return | D41: Sharpe | E41: Max drawdown
B42: 4sight Signal | C42: 0.1715 | D42: 1.52 | E42: -0.122
B43: Price momentum, same rule | C43: 0.0873 | D43: 0.81 | E43: -0.113
B44: Buy and hold the ETF | C44: 0.1054 | D44: 0.7 | E44: -0.272
B45: Hardcoded — computed in Python on the cleaned series (Adj Close returns, 19-Nov-2015 to 06-Jan-2020).
B46: A Sharpe of 1.5 from a single long/flat rule on one ETF is the symptom, not the achievement: it is the look-ahead being monetised.
A48: 5. Sample-period caveat
A49: The sample ends 06-Jan-2020, six weeks before the fastest bear market on record. 88% of the sample is a rising market.
